{
  "orders": [
    {
      "id": "2",
      "customerName": "Fatima",
      "items": [
        "Burger Classic",
        "Frites",
        "Jus d'orange"
      ],
      "totalPrice": 95,
      "status": "accepted",
      "createdAt": "2025-03-16"
    },
    {
      "customerName": "khalid",
      "items": [
        "pizza"
      ],
      "totalPrice": 222,
      "status": "pending",
      "createdAt": "2026-05-05",
      "id": "Z3XQS2xA8O4"
    },
    {
      "id": "3",
      "customerName": "Sara",
      "items": [
        "Tacos",
        "Coca"
      ],
      "totalPrice": 70,
      "status": "completed",
      "createdAt": "2026-05-04"
    },
    {
      "id": "4",
      "customerName": "Youssef",
      "items": [
        "Pizza 4 fromages"
      ],
      "totalPrice": 110,
      "status": "pending",
      "createdAt": "2026-05-03"
    },
    {
      "id": "5",
      "customerName": "Imane",
      "items": [
        "Sandwich poulet",
        "Frites"
      ],
      "totalPrice": 60,
      "status": "rejected",
      "createdAt": "2026-05-02"
    },
    {
      "id": "6",
      "customerName": "Omar",
      "items": [
        "Burger double",
        "Sprite"
      ],
      "totalPrice": 120,
      "status": "accepted",
      "createdAt": "2026-05-01"
    },
    {
      "id": "7",
      "customerName": "Amina",
      "items": [
        "Salade César"
      ],
      "totalPrice": 55,
      "status": "completed",
      "createdAt": "2026-04-30"
    },
    {
      "id": "8",
      "customerName": "Hassan",
      "items": [
        "Panini",
        "Jus citron"
      ],
      "totalPrice": 65,
      "status": "accepted",
      "createdAt": "2026-04-29"
    },
    {
      "id": "9",
      "customerName": "Nadia",
      "items": [
        "Pizza Margherita"
      ],
      "totalPrice": 80,
      "status": "accepted",
      "createdAt": "2026-04-28"
    },
    {
      "id": "10",
      "customerName": "Karim",
      "items": [
        "Tacos XL",
        "Frites",
        "Coca"
      ],
      "totalPrice": 130,
      "status": "completed",
      "createdAt": "2026-04-27"
    }
  ],
  "settings": {
    "restaurantName": "Foodiez",
    "contactEmail": "contact@foodiez.ma"
  },
  "$schema": "./node_modules/json-server/schema.json"
}